delphai_utils/__init__.py
delphai_utils/aio.py
delphai_utils/caching.py
delphai_utils/config.py
delphai_utils/constants/companies.py
delphai_utils/db.py
delphai_utils/elasticsearch.py
delphai_utils/faust.py
delphai_utils/formatting.py
delphai_utils/gateway.py
delphai_utils/grpc/__init__.py
delphai_utils/grpc/authorization.py
delphai_utils/grpc_client.py
delphai_utils/grpc_server.py
delphai_utils/http_server.py
delphai_utils/interceptors/authentication.py
delphai_utils/interceptors/metrics.py
delphai_utils/keycloak.py
delphai_utils/logging.py
delphai_utils/monitoring.py
delphai_utils/patches.py
delphai_utils/retry.py
delphai_utils/strings/similarity.py
delphai_utils/utils.py
delphai_utils/validation.py
delphai_utils/validator.py
delphai_utils-7.3.0.dist-info/METADATA
delphai_utils-7.3.0.dist-info/WHEEL
delphai_utils-7.3.0.dist-info/RECORD
